{
  "transactions": [
    {
      "id": 1,
      "status": "success",
      "issuer": "Garwin Toombs",
      "date": "04/07/2022",
      "price": "$858.15",
      "image": "http://dummyimage.com/188x100.png/ff4444/ffffff"
    },
    {
      "id": 2,
      "status": "failed",
      "issuer": "Raul Gissing",
      "date": "04/07/2022",
      "price": "$842.98",
      "image": "http://dummyimage.com/188x100.png/dddddd/000000"
    },
    {
      "id": 3,
      "status": "success",
      "issuer": "Rozalie Blencoe",
      "date": "02/07/2022",
      "price": "$509.35",
      "image": "http://dummyimage.com/188x100.png/5fa2dd/ffffff"
    },
    {
      "id": 4,
      "status": "failed",
      "issuer": "Ariel Orehead",
      "date": "03/07/2022",
      "price": "$611.39",
      "image": "http://dummyimage.com/188x100.png/dddddd/000000"
    },
    {
      "id": 5,
      "status": "failed",
      "issuer": "Noella Nairne",
      "date": "02/07/2022",
      "price": "$692.45",
      "image": "http://dummyimage.com/188x100.png/5fa2dd/ffffff"
    },
    {
      "id": 6,
      "status": "failed",
      "issuer": "Gardy Jeaves",
      "date": "04/07/2022",
      "price": "$142.24",
      "image": "http://dummyimage.com/188x100.png/cc0000/ffffff"
    },
    {
      "id": 7,
      "status": "failed",
      "issuer": "Joe Kingsford",
      "date": "05/07/2022",
      "price": "$502.89",
      "image": "http://dummyimage.com/188x100.png/dddddd/000000"
    },
    {
      "id": 8,
      "status": "failed",
      "issuer": "Morgen Pavlovic",
      "date": "04/07/2022",
      "price": "$555.29",
      "image": "http://dummyimage.com/188x100.png/5fa2dd/ffffff"
    },
    {
      "id": 9,
      "status": "success",
      "issuer": "Berte O'Scollee",
      "date": "05/07/2022",
      "price": "$948.25",
      "image": "http://dummyimage.com/188x100.png/dddddd/000000"
    },
    {
      "id": 10,
      "status": "failed",
      "issuer": "Cher Itzkovwitch",
      "date": "04/07/2022",
      "price": "$329.29",
      "image": "http://dummyimage.com/188x100.png/dddddd/000000"
    },
    {
      "id": 11,
      "status": "success",
      "issuer": "Emory Sandbrook",
      "date": "04/07/2022",
      "price": "$275.19",
      "image": "http://dummyimage.com/188x100.png/ff4444/ffffff"
    },
    {
      "id": 12,
      "status": "failed",
      "issuer": "Edee Bravington",
      "date": "04/07/2022",
      "price": "$709.92",
      "image": "http://dummyimage.com/188x100.png/5fa2dd/ffffff"
    },
    {
      "id": 13,
      "status": "failed",
      "issuer": "Adiana Newlands",
      "date": "06/07/2022",
      "price": "$664.60",
      "image": "http://dummyimage.com/188x100.png/5fa2dd/ffffff"
    },
    {
      "id": 14,
      "status": "failed",
      "issuer": "Pen Powell",
      "date": "06/07/2022",
      "price": "$475.32",
      "image": "http://dummyimage.com/188x100.png/5fa2dd/ffffff"
    },
    {
      "id": 15,
      "status": "failed",
      "issuer": "Eldon Hubery",
      "date": "04/07/2022",
      "price": "$483.06",
      "image": "http://dummyimage.com/188x100.png/ff4444/ffffff"
    },
    {
      "id": 16,
      "status": "failed",
      "issuer": "Sande Davidofski",
      "date": "05/07/2022",
      "price": "$992.19",
      "image": "http://dummyimage.com/188x100.png/dddddd/000000"
    },
    {
      "id": 17,
      "status": "success",
      "issuer": "Lolita O'Hengerty",
      "date": "05/07/2022",
      "price": "$565.84",
      "image": "http://dummyimage.com/188x100.png/ff4444/ffffff"
    },
    {
      "id": 18,
      "status": "success",
      "issuer": "Rod Maith",
      "date": "05/07/2022",
      "price": "$902.19",
      "image": "http://dummyimage.com/188x100.png/dddddd/000000"
    },
    {
      "id": 19,
      "status": "success",
      "issuer": "Shea Selvester",
      "date": "04/07/2022",
      "price": "$453.39",
      "image": "http://dummyimage.com/188x100.png/cc0000/ffffff"
    },
    {
      "id": 20,
      "status": "success",
      "issuer": "Bar Finden",
      "date": "05/07/2022",
      "price": "$559.73",
      "image": "http://dummyimage.com/188x100.png/5fa2dd/ffffff"
    }
  ]
}
